Workbook

Sheet Sheet1
C2: ÎNTREBĂRI - SEPTEMBRIE 2024 | E2: legea lui Ohm, legile lui Kirchhoff, circuit RLC, conexiuni stea, triunghi transformator, motor, masina sincrona asincrona
B4: ELECTROTEHNICĂ, MAŞINI ŞI REŢELE ELECTRICE | M4: Total | N4: Parcurs | O4: Ramas
M5: 861 | N5: =COUNTA(G7:G867) -> 1 | O5: =M5-N5 -> 860
A6: Nr. | B6: SEPTEMBRIE 2024 Enunt | C6: Varianta a | D6: Varianta b | E6: Varianta c | G6: Raspuns | H6: verif | I6: var a | J6: var b | K6: var c | N6: =N5/M5 -> 0.0011614402
A7: 1 | B7: Atunci când se compensează energia electrica reactiva prin baterii de condensatoare, tensiunea în reţeaua electrica: | C7: scade | D7: nu se modifica | E7: creste | G7: c | H7: =IF(G7=0,"NECOMPLETAT",IF(OR(G7=I7,G7=J7,G7=K7),"CORECT","GRESIT")) -> CORECT | I7: …...... | J7: …...... | K7: c
A8: 2 | B8: Bobinele de stingere din staţiile electrice de transformare sunt echipamente pentru: | C8: compensarea factorului de putere | D8: dotări PSI | E8: compensarea curenţilor capacitivi | H8: =IF(G8=0,"NECOMPLETAT",IF(OR(G8=I8,G8=J8,G8=K8),"CORECT","GRESIT")) -> NECOMPLETAT | I8: …...... | J8: …...... | K8: c
A9: 3 | B9: Câmpul magnetic poate fi produs: | C9: numai de magneţi permanenţi | D9: numai de electromagneţi | E9: de magneţi permanenţi si de electromagneţi | H9: =IF(G9=0,"NECOMPLETAT",IF(OR(G9=I9,G9=J9,G9=K9),"CORECT","GRESIT")) -> NECOMPLETAT | I9: …...... | J9: …...... | K9: c
A10: 4 | B10: 3 condensatoare având capacitatea C1=100 μF, C2=50 μF, C3=100 μF legate în paralel, au capacitatea echivalentă. | C10: 25 μF | D10: 250 μF | E10: 50 μF | H10: =IF(G10=0,"NECOMPLETAT",IF(OR(G10=I10,G10=J10,G10=K10),"CORECT","GRESIT")) -> NECOMPLETAT | I10: …...... | J10: b | K10: …......
A11: 5 | B11: A doua teoremă a lui Kirchhoff, pentru o reţea electrică cu N noduri şi L laturi (L diferit de N), ne furnizează, pentru analiza unui circuit electric: | C11: L+N-1 ecuaţii distincte | D11: L-N +1 ecuaţii distincte | E11: N-L+1 ecuaţii distincte | H11: =IF(G11=0,"NECOMPLETAT",IF(OR(G11=I11,G11=J11,G11=K11),"CORECT","GRESIT")) -> NECOMPLETAT | I11: …...... | J11: b | K11: …......
A12: 6 | B12: AAR se utilizează în scopul: | C12: limitării curenţilor de scurtcircuit; | D12: creşterii continuităţii în alimentare; | E12: reducerii pierderilor de energie pe linii. | H12: =IF(G12=0,"NECOMPLETAT",IF(OR(G12=I12,G12=J12,G12=K12),"CORECT","GRESIT")) -> NECOMPLETAT | I12: …...... | J12: b | K12: …......
A13: 7 | B13: Alunecarea s a unui motor asincron are valori: | C13: cuprinse între 1 si 0 | D13: cuprinse între -1 si 0 | E13: de regulă, mai mari decât 1 | H13: =IF(G13=0,"NECOMPLETAT",IF(OR(G13=I13,G13=J13,G13=K13),"CORECT","GRESIT")) -> NECOMPLETAT | I13: a | J13: …...... | K13: …......
A14: 8 | B14: Aparatul notat cu C pe desenul de mai sus al unei celule prefabricate de medie tensiune de tip închis, reprezintă un: | C14: întreruptor; | D14: transformator de curent; | E14: transformator de tensiune | H14: =IF(G14=0,"NECOMPLETAT",IF(OR(G14=I14,G14=J14,G14=K14),"CORECT","GRESIT")) -> NECOMPLETAT | I14: …...... | J14: b | K14: …......
A15: 9 | B15: Care element nu se foloseşte la reglarea tensiunii în reţelele electrice: | C15: bobina de compensare | D15: transformatorul | E15: rezistorul | H15: =IF(G15=0,"NECOMPLETAT",IF(OR(G15=I15,G15=J15,G15=K15),"CORECT","GRESIT")) -> NECOMPLETAT | I15: …...... | J15: …...... | K15: c
A16: 10 | B16: Cele mai des utilizate pentru serviciile interne ale centralelor electrice sunt: | C16: motoarele de curent continuu | D16: motoarele sincrone | E16: motoarele asincrone | H16: =IF(G16=0,"NECOMPLETAT",IF(OR(G16=I16,G16=J16,G16=K16),"CORECT","GRESIT")) -> NECOMPLETAT | I16: …...... | J16: …...... | K16: c
A17: 11 | B17: Bobinele pentru limitarea curenţilor de scurtcircuit au: | C17: rezistenta mare | D17: inductanţa mare | E17: inductanţa mica | H17: =IF(G17=0,"NECOMPLETAT",IF(OR(G17=I17,G17=J17,G17=K17),"CORECT","GRESIT")) -> NECOMPLETAT | I17: …...... | J17: b | K17: …......
A18: 12 | B18: Câmpul electrostatic este descris | C18: prin: intensitatea câmpului electric | D18: numai prin inducţia electrică | E18: inducţia magnetică | H18: =IF(G18=0,"NECOMPLETAT",IF(OR(G18=I18,G18=J18,G18=K18),"CORECT","GRESIT")) -> NECOMPLETAT | I18: a | J18: …...... | K18: …......
A19: 13 | B19: Comparativ cu cele uscate, transformatoarele imersate prezintă : | C19: o bună rezistenţă la foc; | D19: risc crescut de poluare acustică a mediului ambiant; | E19: necesitatea unor amenajări speciale la instalare | H19: =IF(G19=0,"NECOMPLETAT",IF(OR(G19=I19,G19=J19,G19=K19),"CORECT","GRESIT")) -> NECOMPLETAT | I19: …...... | J19: …...... | K19: c
... A28: 22 | B28: Care dintre relaţiile următoare este adevărată: | C28: inducţia electrică = permitivitatea x intensitatea câmpului electric | D28: inducţia electrică = intensitatea câmpului electric/ permitivitate | E28: inducţia electrică=sarcina x intensitatea câmpului electric | H28: =IF(G28=0,"NECOMPLETAT",IF(OR(G28=I28,G28=J28,G28=K28),"CORECT","GRESIT")) -> NECOMPLETAT | I28: a | J28: …...... | K28: …......
A29: 23 | B29: Care dintre schemele alăturate permite obţinerea a două circuite de cuplă diagonală (cruce cu întreruptor ) ? | H29: =IF(G29=0,"NECOMPLETAT",IF(OR(G29=I29,G29=J29,G29=K29),"CORECT","GRESIT")) -> NECOMPLETAT | I29: a | J29: …...... | K29: …......
A30: 24 | B30: Care dintre schemele alăturate permite obţinerea a două circuite de cuplă longitudinală ( cu întreruptor) ? | H30: =IF(G30=0,"NECOMPLETAT",IF(OR(G30=I30,G30=J30,G30=K30),"CORECT","GRESIT")) -> NECOMPLETAT | I30: a | J30: …...... | K30: …......
A31: 25 | B31: Care dintre schemele alăturate permite obţinerea a două circuite de cuplă transversală ( cu întreruptor) ? | H31: =IF(G31=0,"NECOMPLETAT",IF(OR(G31=I31,G31=J31,G31=K31),"CORECT","GRESIT")) -> NECOMPLETAT | I31: …...... | J31: …...... | K31: c
A32: 26 | B32: Utilizarea unei cuple cu functiuni multiple se prefera atunci cand dorim | C32: scurtarea duratei manevrelor | D32: cresterea continuitatii in alimentare | E32: reducerea investitiei in echiparea statiei. | H32: =IF(G32=0,"NECOMPLETAT",IF(OR(G32=I32,G32=J32,G32=K32),"CORECT","GRESIT")) -> NECOMPLETAT | I32: …...... | J32: b | K32: …......
A33: 27 | B33: Care este energia consumata de o rezistenta electrica r = 10 Ω, prin care trece un curent de 2 A timp de 10 ore: | C33: 200 Wh | D33: 400 Wh | E33: 800 Wh | H33: =IF(G33=0,"NECOMPLETAT",IF(OR(G33=I33,G33=J33,G33=K33),"CORECT","GRESIT")) -> NECOMPLETAT | I33: …...... | J33: b | K33: …......
A34: 28 | B34: Ce posibilităţi de limitare a curenţilor de scurtcirciut sunt de preferat pentru schema de mai sus ? | C34: reducerea t.e.m., acţionând asupra circuitului de excitaţie al generatorului; | D34: mărirea reactanţei schemei de alimentare între sursă şi locul de defect; | E34: creşterea capacităţii de rupere a întreruptoarelor. | H34: =IF(G34=0,"NECOMPLETAT",IF(OR(G34=I34,G34=J34,G34=K34),"CORECT","GRESIT")) -> NECOMPLETAT | I34: …...... | J34: b | K34: …......
A35: 29 | B35: Curentul electric alternativ poate fi produs numai prin fenomene: | C35: termice | D35: chimice | E35: de inducţie electromagnetică | H35: =IF(G35=0,"NECOMPLETAT",IF(OR(G35=I35,G35=J35,G35=K35),"CORECT","GRESIT")) -> NECOMPLETAT | I35: …...... | J35: …...... | K35: c
A36: 30 | B36: Scheme cu un sistem de bare colectoare şi un întreruptor pe circuit sunt folosite | C36: numai pentru staţii de conexiuni de 6 kV | D36: pentru toate treptele de tensiune din reţelele de distribuţie | E36: numai pentru staţii de conexiuni de medie tensiune până la 6o kV | H36: =IF(G36=0,"NECOMPLETAT",IF(OR(G36=I36,G36=J36,G36=K36),"CORECT","GRESIT")) -> NECOMPLETAT | I36: …...... | J36: b | K36: …......
A37: 31 | B37: Celulele prefabricate monobloc se caracterizează în principal prin: | C37: securitate ridicată a persoanelor; | D37: gamă largă de configuraţii ale schemei de conexiuni; | E37: eliminarea totală a posibilităţii de producere a unui scurtcircuit între faze | H37: =IF(G37=0,"NECOMPLETAT",IF(OR(G37=I37,G37=J37,G37=K37),"CORECT","GRESIT")) -> NECOMPLETAT | I37: a | J37: …...... | K37: …......
A38: 32 | B38: Circulaţia câmpului magnetic pe un contur închis este egală cu: | C38: suma algebrică a curenţilor care străbat conturul | D38: zero | E38: suma căderilor de tensiune de-a lungul conturului | H38: =IF(G38=0,"NECOMPLETAT",IF(OR(G38=I38,G38=J38,G38=K38),"CORECT","GRESIT")) -> NECOMPLETAT | I38: a | J38: …...... | K38: …......
A39: 33 | B39: Comparativ cu cele imersate, transformatoarele uscate prezintă : | C39: o bună rezistenţă la foc; | D39: risc redus de poluare acustică a mediului ambiant; | E39: necesitatea unor amenajări speciale la instalare | H39: =IF(G39=0,"NECOMPLETAT",IF(OR(G39=I39,G39=J39,G39=K39),"CORECT","GRESIT")) -> NECOMPLETAT | I39: a | J39: …...... | K39: …......
A40: 34 | B40: Daca la un circuit al unei staţii de 6 sau 20 kV care funcţionează cu neutrul izolat apare o punere monofazatã netã la pământ, tensiunea fata de pământ a celorlalte doua faze: | C40: scade de 1,41 ori | D40: rămâne constanta | E40: creste de 1,73 ori | H40: =IF(G40=0,"NECOMPLETAT",IF(OR(G40=I40,G40=J40,G40=K40),"CORECT","GRESIT")) -> NECOMPLETAT | I40: …...... | J40: …...... | K40: c
A41: 35 | B41: Compartimentarea unei celule electrice se utilizează | C41: în scopul evitării extinderii avariilor; | D41: numai în scopul protejării personalului de exploatare; | E41: protecţiei la supratensiuni | H41: =IF(G41=0,"NECOMPLETAT",IF(OR(G41=I41,G41=J41,G41=K41),"CORECT","GRESIT")) -> NECOMPLETAT | I41: a | J41: …...... | K41: …......
A42: 36 | B42: Compartimentul notat cu 2 pe desenul de mai sus al unei celule prefabricate de medie tensiune de tip închis, reprezintă: | C42: compartimentul de legătură cu reţeaua electrică; | D42: compartimentul aparatajului de comutaţie; | E42: compartimentul circuitelor secundare. | H42: =IF(G42=0,"NECOMPLETAT",IF(OR(G42=I42,G42=J42,G42=K42),"CORECT","GRESIT")) -> NECOMPLETAT | I42: …...... | J42: b | K42: …......
A43: 37 | B43: Compartimentul notat cu 3 pe desenul de mai sus al unei celule prefabricate de medie tensiune de tip închis, reprezintă: | C43: compartimentul de legătură cu reţeaua electrică; | D43: compartimentul aparatajului de comutaţie; | E43: compartimentul circuitelor secundare. | H43: =IF(G43=0,"NECOMPLETAT",IF(OR(G43=I43,G43=J43,G43=K43),"CORECT","GRESIT")) -> NECOMPLETAT | I43: a | J43: …...... | K43: …......
... A77: 71 | B77: Extinderea domeniului de măsurare la voltmetre se realizează cu: | C77: shunturi | D77: rezistente adiţionale | E77: condensatoare montate în paralel | H77: =IF(G77=0,"NECOMPLETAT",IF(OR(G77=I77,G77=J77,G77=K77),"CORECT","GRESIT")) -> NECOMPLETAT | I77: …...... | J77: b | K77: …......
A78: 72 | B78: Factorul de atenuare al unui circuit format dintr-un rezistor de rezistenţă R înseriat cu o bobină de inductanţă L, alimentate de o tensiune electromotoare constantă este egal cu: | C78: R/L | D78: L/R | E78: 1 | H78: =IF(G78=0,"NECOMPLETAT",IF(OR(G78=I78,G78=J78,G78=K78),"CORECT","GRESIT")) -> NECOMPLETAT | I78: …...... | J78: b | K78: …......
A79: 73 | B79: Fluxul electric total, produs de o sarcină electrică de valoare q printr-o suprafaţă închisă care o înconjoară, este egal cu: | C79: valoarea numerică 2q | D79: valoarea numerică q | E79: valoarea numerică q/2 | H79: =IF(G79=0,"NECOMPLETAT",IF(OR(G79=I79,G79=J79,G79=K79),"CORECT","GRESIT")) -> NECOMPLETAT | I79: …...... | J79: b | K79: …......
A80: 74 | B80: Folosirea conductoarelor jumelate în construcţia LEA are ca scop principal: | C80: reducerea pierderilor Corona | D80: reducerea solicitărilor mecanice ale stâlpilor | E80: reducerea curenţilor de scurtcircuit | H80: =IF(G80=0,"NECOMPLETAT",IF(OR(G80=I80,G80=J80,G80=K80),"CORECT","GRESIT")) -> NECOMPLETAT | I80: a | J80: …...... | K80: …......
A81: 75 | B81: Formula de calcul a frecventei produsa în sistemul electroenergetic de un generator cu n [rot/min] si p perechi de poli este: | C81: f =n p / 60 | D81: f = 60 n / p | E81: f = 60 p / n | H81: =IF(G81=0,"NECOMPLETAT",IF(OR(G81=I81,G81=J81,G81=K81),"CORECT","GRESIT")) -> NECOMPLETAT | I81: a | J81: …...... | K81: …......
A82: 76 | B82: Formula e = B l v, unde e este tensiune electromotoare, B este inducţia magnetică, l este lungimea unui conductor, v este viteza de deplasare a acestuia, reprezintă o forma particulară a: | C82: teoremelor Biot-Savart | D82: legii inducţiei electromagnetice | E82: legii circuitului magnetic | H82: =IF(G82=0,"NECOMPLETAT",IF(OR(G82=I82,G82=J82,G82=K82),"CORECT","GRESIT")) -> NECOMPLETAT | I82: …...... | J82: b | K82: …......
A83: 77 | B83: Forţa care se exercită asupra unui conductor rectiliniu, parcurs de curentul i, aflat în câmpul de inducţie magnetică B se numeşte: | C83: forţă electromagnetică (Laplace) | D83: forţă electrodinamică | E83: forţă magnetomotoare | H83: =IF(G83=0,"NECOMPLETAT",IF(OR(G83=I83,G83=J83,G83=K83),"CORECT","GRESIT")) -> NECOMPLETAT | I83: a | J83: …...... | K83: …......
A84: 78 | B84: Forţa care se exercită între două conductoare străbătute de curenţi electrici se numeşte: | C84: forţă electrocinetică | D84: forţă electrodinamică | E84: forţă magnetomotoare | H84: =IF(G84=0,"NECOMPLETAT",IF(OR(G84=I84,G84=J84,G84=K84),"CORECT","GRESIT")) -> NECOMPLETAT | I84: …...... | J84: b | K84: …......
A85: 79 | B85: Tensiunea electromotoare indusă într-un circuit închis, prin variaţia fluxului magnetic, este: | C85: direct proporţională cu variaţia în timp a fluxului magnetic | D85: invers proporţională cu variaţia în timp a fluxului magnetic | E85: dependentă de modul în care este produs fluxul magnetic | H85: =IF(G85=0,"NECOMPLETAT",IF(OR(G85=I85,G85=J85,G85=K85),"CORECT","GRESIT")) -> NECOMPLETAT | I85: a | J85: …...... | K85: …......
A86: 80 | B86: Forţa electrodinamică exercitată între două conductoare filiforme, paralele, lungi, aflate la distanţa r, străbătute de câte un curent: | C86: este direct proporţională cu distanţa r dintre conductoare | D86: este invers proporţională cu distanţa r dintre conductoare | E86: nu depinde de distanţa r dintre conductoare | H86: =IF(G86=0,"NECOMPLETAT",IF(OR(G86=I86,G86=J86,G86=K86),"CORECT","GRESIT")) -> NECOMPLETAT | I86: …...... | J86: b | K86: …......
A87: 81 | B87: Forţa F care se exercită asupra unei sarcini electrice q aflată într-un câmp electric de intensitate E are expresia: | C87: F=E/q | D87: F=qE | E87: F=q/E | H87: =IF(G87=0,"NECOMPLETAT",IF(OR(G87=I87,G87=J87,G87=K87),"CORECT","GRESIT")) -> NECOMPLETAT | I87: …...... | J87: b | K87: …......
A88: 82 | B88: Frecvenţa unei mărimi periodice este inversul: | C88: amplitudinii | D88: perioadei | E88: fazei | H88: =IF(G88=0,"NECOMPLETAT",IF(OR(G88=I88,G88=J88,G88=K88),"CORECT","GRESIT")) -> NECOMPLETAT | I88: …...... | J88: b | K88: …......
A89: 83 | B89: Funcţionarea contoarelor de inducţie are la baza: | C89: curenţii turbionari | D89: efectul termic al curentului electric | E89: forţa electrostatica | H89: =IF(G89=0,"NECOMPLETAT",IF(OR(G89=I89,G89=J89,G89=K89),"CORECT","GRESIT")) -> NECOMPLETAT | I89: a | J89: …...... | K89: …......
A90: 84 | B90: În instalaţiile de joasa tensiune, legarea la pământ este justificatã: | C90: din motive economice | D90: pentru diminuarea suprasolicitărilor echipamentelor electrice | E90: pentru securitatea muncii | H90: =IF(G90=0,"NECOMPLETAT",IF(OR(G90=I90,G90=J90,G90=K90),"CORECT","GRESIT")) -> NECOMPLETAT | I90: …...... | J90: …...... | K90: c
... A159: 153 | B159: Mărimea caracteristică circuitelor magnetice şi care este analoagă cu rezistenţa circuitelor electrice se numeşte: | C159: impedanţă | D159: reluctanţă | E159: permeanţă | H159: =IF(G159=0,"NECOMPLETAT",IF(OR(G159=I159,G159=J159,G159=K159),"CORECT","GRESIT")) -> NECOMPLETAT | I159: …...... | J159: b | K159: …......
A160: 154 | B160: Mărimea periodică alternativă este o mărime a cărei valoare medie în decursul unei perioade este egală cu: | C160: 1 | D160: 0 | E160: 1,5 | H160: =IF(G160=0,"NECOMPLETAT",IF(OR(G160=I160,G160=J160,G160=K160),"CORECT","GRESIT")) -> NECOMPLETAT | I160: …...... | J160: b | K160: …......
A161: 155 | B161: Mărirea cuplului de pornire şi micşorarea curentului de pornire la motoarele asincrone cu rotorul în scurtcircuit se face: | C161: prin deconectarea şi reconectarea lor la reţeaua de alimentare | D161: numai prin utilizarea motoarelor cu rotorul în dublă colivie | E161: prin utilizarea motoarelor cu rotorul în colivie cu bare înalte | H161: =IF(G161=0,"NECOMPLETAT",IF(OR(G161=I161,G161=J161,G161=K161),"CORECT","GRESIT")) -> NECOMPLETAT | I161: …...... | J161: …...... | K161: c
A162: 156 | B162: Pe liniile electrice de înaltă tensiune, unde se preferă montarea transformatoarelor de curent ?: | C162: între barele colectoare şi separatorul de bare; | D162: între separatorul de bare şi întreruptor; | E162: între întreruptor şi separatorul de linie. | H162: =IF(G162=0,"NECOMPLETAT",IF(OR(G162=I162,G162=J162,G162=K162),"CORECT","GRESIT")) -> NECOMPLETAT | I162: …...... | J162: …...... | K162: c
A163: 157 | B163: Metoda transfigurării reţelelor electrice este folosita pentru a: | C163: reduce pierderile de putere activa în reţea | D163: simplifica structura reţelelor echivalente pentru a reduce volumul de calcule | E163: diminua consumul specific de material conductor | H163: =IF(G163=0,"NECOMPLETAT",IF(OR(G163=I163,G163=J163,G163=K163),"CORECT","GRESIT")) -> NECOMPLETAT | I163: …...... | J163: b | K163: …......
A164: 158 | B164: Miezul magnetic al rotorului unei maşini electrice asincrone se realizează din tole pentru: | C164: reducerea curenţilor turbionari | D164: reducerea tensiunii electromotoare induse | E164: numai din motive constructive | H164: =IF(G164=0,"NECOMPLETAT",IF(OR(G164=I164,G164=J164,G164=K164),"CORECT","GRESIT")) -> NECOMPLETAT | I164: a | J164: …...... | K164: …......
A165: 159 | B165: Montajul fix al aparatelor în interiorul celulelor conduce la: | C165: realizări constructive simple, fără blocaje suplimentare; | D165: reducerea dimensiunilor celulelor; | E165: reducerea timpului necesar reviziilor şi reparaţiilor. | H165: =IF(G165=0,"NECOMPLETAT",IF(OR(G165=I165,G165=J165,G165=K165),"CORECT","GRESIT")) -> NECOMPLETAT | I165: a | J165: …...... | K165: …......
A166: 160 | B166: Motoarele sincrone se utilizează rar pentru antrenarea mecanismelor de servicii proprii din centralele electrice | C166: deoarece nu permit variaţia turaţiei în limite largi | D166: numai deoarece excitatoarea cu colector din circuitul acestora este un element puţin fiabil | E166: deoarece au randament mai mic decât al celorlalte tipuri de motoare | H166: =IF(G166=0,"NECOMPLETAT",IF(OR(G166=I166,G166=J166,G166=K166),"CORECT","GRESIT")) -> NECOMPLETAT | I166: a | J166: …...... | K166: …......
A167: 161 | B167: Nivelul de tensiune în sistem se reglează | C167: încărcarea generatoarelor cu putere activa | D167: numai prin încărcarea generatoarelor cu putere reactiva | E167: prin utilizare de compensatoare | H167: =IF(G167=0,"NECOMPLETAT",IF(OR(G167=I167,G167=J167,G167=K167),"CORECT","GRESIT")) -> NECOMPLETAT | I167: …...... | J167: …...... | K167: c
A168: 162 | B168: O linie electrică foarte lungă se comportă ca o linie adaptată: | C168: dacă alimentează un receptor cu impedanţă egală cu impedanţa sa caracteristică | D168: dacă funcţionează în scurtcircuit | E168: dacă funcţionează în gol | H168: =IF(G168=0,"NECOMPLETAT",IF(OR(G168=I168,G168=J168,G168=K168),"CORECT","GRESIT")) -> NECOMPLETAT | I168: a | J168: …...... | K168: …......
A169: 163 | B169: O linie electrică lungă funcţionând în gol: | C169: produce putere reactivă | D169: absoarbe putere reactivă | E169: nu produce şi nu absoarbe putere reactivă | H169: =IF(G169=0,"NECOMPLETAT",IF(OR(G169=I169,G169=J169,G169=K169),"CORECT","GRESIT")) -> NECOMPLETAT | I169: a | J169: …...... | K169: …......
A170: 164 | B170: O linie electrică lungă funcţionând în scurtcircuit: | C170: absoarbe putere reactivă | D170: produce putere reactivă | E170: nu produce şi nu absoarbe putere reactivă | H170: =IF(G170=0,"NECOMPLETAT",IF(OR(G170=I170,G170=J170,G170=K170),"CORECT","GRESIT")) -> NECOMPLETAT | I170: a | J170: …...... | K170: …......
A171: 165 | B171: O protecţie este selectivă atunci când: | C171: deconectează numai consumatorul defect | D171: deconectează toţi consumatorii | E171: deconectează o jumătate dintre consumatori | H171: =IF(G171=0,"NECOMPLETAT",IF(OR(G171=I171,G171=J171,G171=K171),"CORECT","GRESIT")) -> NECOMPLETAT | I171: a | J171: …...... | K171: …......
A172: 166 | B172: Pe măsură ce creşte tensiunea la care se realizează instalaţiile electrice, costul pierderilor de putere Cp este: | C172: constant | D172: crescător | E172: descrescător | H172: =IF(G172=0,"NECOMPLETAT",IF(OR(G172=I172,G172=J172,G172=K172),"CORECT","GRESIT")) -> NECOMPLETAT | I172: …...... | J172: …...... | K172: c
... A223: 217 | B223: Schema echivalentă de calcul în cazul producerii unui scurtcircuit între două faze ale unei reţele izolat de pământ şi fără arc electric se compune din: | C223: schema de secvenţă directă (pozitivă) înseriată cu triplul impedanţei arcului | D223: schemele de secvenţă directă (pozitivă) şi inversă (negativă) conectate în paralel | E223: schemele de secvenţă directă (pozitivă), inversă (negativă) şi homopolară (zero) conectate în paralel | H223: =IF(G223=0,"NECOMPLETAT",IF(OR(G223=I223,G223=J223,G223=K223),"CORECT","GRESIT")) -> NECOMPLETAT | I223: …...... | J223: b | K223: …......
A224: 218 | B224: Schema echivalentă de calcul în cazul producerii unui scurtcircuit trifazat, al unei reţele, izolat de pământ se compune din: | C224: schemele de secvenţă directă (pozitivă) , inversă (negativă) şi homopolară (zero) conectate în serie | D224: schema de secvenţă directă (pozitivă) | E224: schemele de secvenţă directă (pozitivă) şi inversă (negativă) conectate în paralel | H224: =IF(G224=0,"NECOMPLETAT",IF(OR(G224=I224,G224=J224,G224=K224),"CORECT","GRESIT")) -> NECOMPLETAT | I224: …...... | J224: b | K224: …...... | M224: x
A225: 219 | B225: Schema echivalentă de calcul în cazul producerii unui scurtcircuit trifazat şi la pământ, cu arc, se compune din: | C225: schema de secvenţă directă (pozitivă) înseriată cu triplul impedanţei arcului | D225: schema de secvenţă directă (pozitivă) | E225: schema de secvenţă directă (pozitivă) înseriată cu schema de secvenţă inversă (negativă). | H225: =IF(G225=0,"NECOMPLETAT",IF(OR(G225=I225,G225=J225,G225=K225),"CORECT","GRESIT")) -> NECOMPLETAT | I225: a | J225: …...... | K225: …......
A226: 220 | B226: Transformatoarele de măsură se folosesc | C226: în instalaţiile de curent alternativ de înaltă tensiune | D226: numai în instalaţiile de curent alternativ de medie tensiune | E226: în instalaţiile de curent continuu de înaltă şi joasă tensiune | H226: =IF(G226=0,"NECOMPLETAT",IF(OR(G226=I226,G226=J226,G226=K226),"CORECT","GRESIT")) -> NECOMPLETAT | I226: a | J226: …...... | K226: …......
A227: 221 | B227: Scopul normării distanţelor de izolare în aer minime admisibile pentru instalaţiile electrice este asigurarea: | C227: protecţiei personalului de exploatare a instalaţiei; | D227: siguranţei în funcţionare a instalaţiei, prin reducerea numărului de defecte în instalaţie; | E227: realizării unei economii de teren. | H227: =IF(G227=0,"NECOMPLETAT",IF(OR(G227=I227,G227=J227,G227=K227),"CORECT","GRESIT")) -> NECOMPLETAT | I227: …...... | J227: b | K227: …......
A228: 222 | B228: Susceptanţa unui circuit de curent alternativ sinusoidal este inversul: | C228: impedanţei | D228: rezistenţei | E228: reactanţei | H228: =IF(G228=0,"NECOMPLETAT",IF(OR(G228=I228,G228=J228,G228=K228),"CORECT","GRESIT")) -> NECOMPLETAT | I228: …...... | J228: …...... | K228: c
A229: 223 | B229: Transformatoarele de măsurare de curent: | C229: pot fi racordate în circuitul primar cu înfăşurarea secundara deschisa | D229: pot fi lăsate în exploatare cu înfăşurarea secundara deschisa | E229: nu pot fi racordate in circuitul primar cu înfăşurarea secundara deschisa | H229: =IF(G229=0,"NECOMPLETAT",IF(OR(G229=I229,G229=J229,G229=K229),"CORECT","GRESIT")) -> NECOMPLETAT | I229: …...... | J229: …...... | K229: c
A230: 224 | B230: Secţionarea barelor colectoare ale unei staţii electrice conduce | C230: la mărirea continuităţii în alimentare a consumatorilor racordaţi la bare; | D230: limitarea curenţilor de scurtcircuit pe barele respective, dacă alimentarea staţiei se face printr-un singur transformator; | E230: numai la limitarea curenţilor de scurtcircuit pe barele respective, dacă alimentarea staţiei se face prin două transformatoare sau printr-un transformator cu înfăşurare divizată. | H230: =IF(G230=0,"NECOMPLETAT",IF(OR(G230=I230,G230=J230,G230=K230),"CORECT","GRESIT")) -> NECOMPLETAT | I230: a | J230: …...... | K230: …......
A231: 225 | B231: Secţionarea barelor colectoare în staţiile electrice are scopul: | C231: de limitare a curenţilor de scurtcircuit | D231: de a reduce costul instalaţiei | E231: de a reduce pierderile de putere | H231: =IF(G231=0,"NECOMPLETAT",IF(OR(G231=I231,G231=J231,G231=K231),"CORECT","GRESIT")) -> NECOMPLETAT | I231: a | J231: …...... | K231: …......
A232: 226 | B232: Sensul puterii deformante într-un circuit format dintr-un generator care produce o undă sinusoidală şi o bobină cu miez de fier saturat este: | C232: de la generator spre bobină | D232: întotdeauna de la bobină spre generator | E232: poate avea oricare sens, în funcţie de încărcarea generatorului | H232: =IF(G232=0,"NECOMPLETAT",IF(OR(G232=I232,G232=J232,G232=K232),"CORECT","GRESIT")) -> NECOMPLETAT | I232: …...... | J232: b | K232: …......
A233: 227 | B233: Separatorul, ca echipament în cadrul unei staţii electrice, are rolul: | C233: de a proteja circuitul la supracurenţi | D233: de a separa vizibil un circuit | E233: de a măsură nivelul de izolaţie | H233: =IF(G233=0,"NECOMPLETAT",IF(OR(G233=I233,G233=J233,G233=K233),"CORECT","GRESIT")) -> NECOMPLETAT | I233: …...... | J233: b | K233: …......
A234: 228 | B234: Siguranţele electrice au rolul de a: | C234: proteja instalaţia din aval la defecte la scurtcircuit ca si la suprasarcini de lunga durata | D234: face trecerea din linie electrica aeriana în line electrica în cablu | E234: asigura protecţia personalului | H234: =IF(G234=0,"NECOMPLETAT",IF(OR(G234=I234,G234=J234,G234=K234),"CORECT","GRESIT")) -> NECOMPLETAT | I234: a | J234: …...... | K234: …......
A235: 229 | B235: Siguranţele electrice sunt aparate electrice care împiedica: | C235: creşterea tensiunii peste o valoare limita | D235: creşterea curentului peste o valoare limita | E235: scăderea curentului sub o valoare limita | H235: =IF(G235=0,"NECOMPLETAT",IF(OR(G235=I235,G235=J235,G235=K235),"CORECT","GRESIT")) -> NECOMPLETAT | I235: …...... | J235: b | K235: …......
A236: 230 | B236: Siguranţele fuzibile sunt aparate utilizate pentru protecţie la: | C236: supratensiuni | D236: supracurenţi | E236: defect de izolaţie | H236: =IF(G236=0,"NECOMPLETAT",IF(OR(G236=I236,G236=J236,G236=K236),"CORECT","GRESIT")) -> NECOMPLETAT | I236: …...... | J236: b | K236: …......
... A276: 270 | B276: Utilizarea SF6 ca mediu de stingere a arcului electric permite | C276: doar realizarea unor întreruptoare fără pericol de incendiu; | D276: realizarea unor întreruptoare cu întreţinere mult simplificată; | E276: puţin silenţioase. | H276: =IF(G276=0,"NECOMPLETAT",IF(OR(G276=I276,G276=J276,G276=K276),"CORECT","GRESIT")) -> NECOMPLETAT | I276: …...... | J276: b | K276: …......
A277: 271 | B277: Utilizarea vidului ca mediu de stingere a arcului electric: | C277: reduce pericolul de incendiu; | D277: nu reduce cheltuielile de întreţinere; | E277: creşte masa şi gabaritul întreruptoarelor | H277: =IF(G277=0,"NECOMPLETAT",IF(OR(G277=I277,G277=J277,G277=K277),"CORECT","GRESIT")) -> NECOMPLETAT | I277: a | J277: …...... | K277: …...... | M277: EXEMPLE DE ÎNTREBĂRI IANUARIE 2024 | R277: EXEMPLE DE ÎNTREBĂRI IANUARIE 2024
A278: 272 | B278: Valoarea frecventei în sistemul electroenergetic este determinata în principal de: | C278: bilanţul puterilor active | D278: circulaţia puterii reactive | E278: modul de tratare a neutrului reţelei | H278: =IF(G278=0,"NECOMPLETAT",IF(OR(G278=I278,G278=J278,G278=K278),"CORECT","GRESIT")) -> NECOMPLETAT | I278: a | J278: …...... | K278: …...... | R278: NORME TEHNICE Gr. IIIB şi IVB
A279: 273 | B279: Valoarea medie a capacităţii lineice pentru o linie electrică aeriană trifazată este ......... faţă de cea a unui cablu subteran. | C279: egală | D279: mai mică | E279: mai mare | H279: =IF(G279=0,"NECOMPLETAT",IF(OR(G279=I279,G279=J279,G279=K279),"CORECT","GRESIT")) -> NECOMPLETAT | I279: …...... | J279: b | K279: …...... | M279: NORME TEHNICE Gr. IIIA şi IVA
A280: 274 | B280: Valoarea medie a inductanţei de serviciu pentru o linie electrică aeriană trifazată este ......... faţă de cea a unui cablu subteran. | C280: egală | D280: mai mare | E280: mai mică | H280: =IF(G280=0,"NECOMPLETAT",IF(OR(G280=I280,G280=J280,G280=K280),"CORECT","GRESIT")) -> NECOMPLETAT | I280: …...... | J280: b | K280: …......
A281: 275 | B281: Valoarea medie pătratică a unei mărimi periodice se mai numeşte şi: | C281: amplitudine | D281: modul | E281: valoare efectivă sau valoarea eficace | H281: =IF(G281=0,"NECOMPLETAT",IF(OR(G281=I281,G281=J281,G281=K281),"CORECT","GRESIT")) -> NECOMPLETAT | I281: …...... | J281: …...... | K281: c | M281: IANUARIE 2024 Enunt | N281: Varianta a | O281: Varianta b | P281: Varianta c | R281: IANUARIE 2024 Enunt | S281: Varianta a | T281: Varianta b | U281: Varianta c
A282: 276 | B282: Atunci când secţiunea conductorului neutru este cel puţin egală sau echivalentă cu a conductorului de fază, | C282: este necesar să se prevadă o protecţie de supracurent pe conductorul neutru, dar numai dacă rețeaua este de tip TN | D282: nu este necesar să se prevadă o protecţie de supracurent pe conductorul neutru dacă rețeaua este de tip TT | E282: în nici o situație nu este cazul să se prevadă o protecţie de supracurent pe conductorul neutru dacă rețeaua este de tip IT | H282: =IF(G282=0,"NECOMPLETAT",IF(OR(G282=I282,G282=J282,G282=K282),"CORECT","GRESIT")) -> NECOMPLETAT | I282: …...... | J282: …...... | K282: c
A283: 277 | B283: Dacă de la orice punct al unei instalaţii funcţiile de conductor neutru (N) şi de conductor de protecţie (PE) sunt asigurate prin conductoare separate, | C283: este permis să se conecteze conductorul neutru la orice altă parte a instalaţiei legată la pământ | D283: este permis să se conecteze conductorul neutru la orice altă parte a instalaţiei legată la pământ, în anumite situații | E283: nu este permis să se conecteze conductorul neutru la orice altă parte a instalaţiei legată la pământ | H283: =IF(G283=0,"NECOMPLETAT",IF(OR(G283=I283,G283=J283,G283=K283),"CORECT","GRESIT")) -> NECOMPLETAT | I283: …...... | J283: …...... | K283: c
A284: 278 | B284: Dacă de la orice punct al unei instalaţii funcţiile de conductor neutru (N) şi de conductor de protecţie (PE) sunt asigurate prin conductoare separate, | C284: Se prevede bornă sau bară comune pentru conductoarele de neutru şi respectiv conductoarele de protecţie. | D284: Se prevăd borne sau bare separate pentru conductoarele de neutru şi respectiv conductoarele de protecţie. | E284: Se prevăd borne sau bare separate pentru conductoarele de neutru şi respectiv conductoarele de protecţie, în anumite situații | H284: =IF(G284=0,"NECOMPLETAT",IF(OR(G284=I284,G284=J284,G284=K284),"CORECT","GRESIT")) -> NECOMPLETAT | I284: …...... | J284: b | K284: …......
A285: 279 | B285: Adâncimea de pozare în pământ a tuburilor sau a blocurilor de cabluri: | C285: trebuie aleasă conform condiţiilor locale | D285: trebuie să respecte valorile minime prevăzute în norme | E285: trebuie să fie de minim 50 cm | H285: =IF(G285=0,"NECOMPLETAT",IF(OR(G285=I285,G285=J285,G285=K285),"CORECT","GRESIT")) -> NECOMPLETAT | I285: …...... | J285: b | K285: …......
A286: 280 | B286: Amplasarea instalaţiilor electrice de joasă tensiune pe trasee comune cu acelea ale altor instalaţii sau utilaje care ar putea să le pericliteze în funcţionare normală sau în caz de avarie: | C286: este interzisă | D286: trebuie evitată | E286: este opţiunea proiectantului | H286: =IF(G286=0,"NECOMPLETAT",IF(OR(G286=I286,G286=J286,G286=K286),"CORECT","GRESIT")) -> NECOMPLETAT | I286: …...... | J286: b | K286: …......
A287: 281 | B287: Atunci când între priza de pământ a clădirii şi priza de pământ a postului de transformare (ce alimentează clădirea) este o distanță mai mică decât cea prevăzută de norme, se prevede o priză de pământ comună cu rezistenţă de cel mult | C287: 10 Ω | D287: 1 Ω. | E287: 4 Ω | H287: =IF(G287=0,"NECOMPLETAT",IF(OR(G287=I287,G287=J287,G287=K287),"CORECT","GRESIT")) -> NECOMPLETAT | I287: …...... | J287: b | K287: …......
A288: 282 | B288: Conductoarele, barele, tuburile etc. | C288: nu se pot dispune pe trasee comune cu traseele altor instalaţii | D288: se pot dispune pe trasee comune cu traseele altor instalaţii cu îndeplinirea unor condiţii | E288: se pot dispune pe trasee comune cu traseele altor instalaţii, fără alte condiții, dacă sunt în montaj aparent. | H288: =IF(G288=0,"NECOMPLETAT",IF(OR(G288=I288,G288=J288,G288=K288),"CORECT","GRESIT")) -> NECOMPLETAT | I288: …...... | J288: b | K288: …......
A289: 283 | B289: Conform prevederilor I 7 - 2011, alegerea secţiunii conductoarelor şi barelor din interiorul unui tablou este responsabilitatea . | C289: proiectantului instalației electrice | D289: producătorului | E289: verificatorului de proiect | H289: =IF(G289=0,"NECOMPLETAT",IF(OR(G289=I289,G289=J289,G289=K289),"CORECT","GRESIT")) -> NECOMPLETAT | I289: …...... | J289: b | K289: …......
A290: 284 | B290: Dacă circuitul unei baterii de condensatoare se protejează cu întreruptor automat (disjunctor) acesta se reglează pentru protecție la suprasarcină la | C290: curentul nominal al bateriei; | D290: 1,5 ori curentul nominal al bateriei; | E290: 1,2 ori curentul nominal al bateriei; | H290: =IF(G290=0,"NECOMPLETAT",IF(OR(G290=I290,G290=J290,G290=K290),"CORECT","GRESIT")) -> NECOMPLETAT | I290: …...... | J290: b | K290: …......
A291: 285 | B291: Dacă instalaţiile electrice sunt în distribuţie prefabricată în învelişuri metalice (cutii, carcase), aceste învelişuri | C291: pot fi utilizate drept conductoare de protecţie, în anumite condiții | D291: nu pot fi utilizate drept conductoare de protecţie | E291: pot fi utilizate întotdeauna drept conductoare de protecţie | H291: =IF(G291=0,"NECOMPLETAT",IF(OR(G291=I291,G291=J291,G291=K291),"CORECT","GRESIT")) -> NECOMPLETAT | I291: a | J291: …...... | K291: …......
A292: 286 | B292: Descărcătorul cu coarne | C292: asigură întotdeauna stingerea arcului electric al curentului de însoţire | D292: este constituit din unul sau mai multe eclatoare în aer | E292: realizează uneori funcţia de protecţie prin reducerea nivelului supratensiunilor. | H292: =IF(G292=0,"NECOMPLETAT",IF(OR(G292=I292,G292=J292,G292=K292),"CORECT","GRESIT")) -> NECOMPLETAT | I292: …...... | J292: b | K292: …......
A293: 287 | B293: Dozele de derivaţie se instalează | C293: numai pe suprafeţele verticale ale elementelor de construcţii | D293: cu prioritate pe suprafeţele verticale ale elementelor de construcţii | E293: pe sau în pardoseală, indiferent de tipul dozei | H293: =IF(G293=0,"NECOMPLETAT",IF(OR(G293=I293,G293=J293,G293=K293),"CORECT","GRESIT")) -> NECOMPLETAT | I293: …...... | J293: b | K293: …......
... A296: 290 | B296: În cazul în care alimentarea consumatorului se face din cofretul de branşament de joasă tensiune, valorile căderilor de tensiune, în regim normal de funcţionare faţă de tensiunea nominală a reţelei, trebuie să fie de cel mult: | C296: 3% pentru receptoarele din instalaţiile electrice de lumină şi 5% pentru restul receptoarelor (forţă etc.) | D296: 10% pentru toate tipurile de receptoare | E296: 5% pentru receptoarele din instalaţiile electrice de lumină şi 12% pentru restul receptoarelor (forţă etc.) | H296: =IF(G296=0,"NECOMPLETAT",IF(OR(G296=I296,G296=J296,G296=K296),"CORECT","GRESIT")) -> NECOMPLETAT | I296: a | J296: …...... | K296: …......
A297: 291 | B297: În cazul instalaţiilor electrice de alimentare a motoarelor electrice, pierderea de tensiune la pornire, faţă de tensiunea nominală (dacă nu se dispune de alte date specificate de producătorul motorului etc.), trebuie să fie cel mult egală cu: | C297: 0.2 | D297: 0.25 | E297: 0.12 | H297: =IF(G297=0,"NECOMPLETAT",IF(OR(G297=I297,G297=J297,G297=K297),"CORECT","GRESIT")) -> NECOMPLETAT | I297: …...... | J297: …...... | K297: c
A298: 292 | B298: În cazul unei clădiri alimentate dintr-un post de transformare : | C298: se prevăd întotdeauna prize de pământ separate, la clădire și la postul de transformare | D298: în anumite situații se prevede o priză de pământ comună cu rezistenţă de cel mult 1 Ω. | E298: în anumite situații se prevede o priză de pământ comună cu rezistenţă de cel mult 4 Ω. | H298: =IF(G298=0,"NECOMPLETAT",IF(OR(G298=I298,G298=J298,G298=K298),"CORECT","GRESIT")) -> NECOMPLETAT | I298: …...... | J298: b | K298: …......
A299: 293 | B299: În cazul unei clădiri alimentate dintr-un post de transformare, între priza de pământ a clădirii şi priza de pământ a postului de transformare trebuie să fie o distanţă de: | C299: cel mult 1000 m | D299: cel puţin 20 m | E299: cel puţin 40 m | H299: =IF(G299=0,"NECOMPLETAT",IF(OR(G299=I299,G299=J299,G299=K299),"CORECT","GRESIT")) -> NECOMPLETAT | I299: …...... | J299: b | K299: …......
A300: 294 | B300: În fiecare instalaţie la nivelul tabloului general trebuie prevăzută | C300: o bornă / bară principală de legare la pământ, numai atunci când reţeaua de distribuţie este TN-C; | D300: o bornă / bară principală de legare la pământ, | E300: o bornă / bară principală de legare la pământ, numai în cazul în care alimentarea receptoarelor se face în sistem TN-S | H300: =IF(G300=0,"NECOMPLETAT",IF(OR(G300=I300,G300=J300,G300=K300),"CORECT","GRESIT")) -> NECOMPLETAT | I300: …...... | J300: b | K300: …......
A301: 295 | B301: În instalaţiile electrice cu tensiunea nominală până la 35 kV inclusiv, transformatoarele de tensiune racordate la barele colectoare vor fi, de regulă, protejate cu: | C301: siguranţe fuzibile | D301: separatoare | E301: separatoare de sarcină | H301: =IF(G301=0,"NECOMPLETAT",IF(OR(G301=I301,G301=J301,G301=K301),"CORECT","GRESIT")) -> NECOMPLETAT | I301: a | J301: …...... | K301: …......
A302: 296 | B302: În mod special se prevăd conductoare din cupru la circuitele electrice pentru alimentarea de sisteme şi instalaţii de prevenire şi stingere a incendiilor, atunci când secţiunea conductoarelor din aluminiu ar rezulta mai mică de: | C302: 16 mm2 | D302: 25 mm2 | E302: 10 mm2 | H302: =IF(G302=0,"NECOMPLETAT",IF(OR(G302=I302,G302=J302,G302=K302),"CORECT","GRESIT")) -> NECOMPLETAT | I302: …...... | J302: …...... | K302: c
...

Sheet QUIZ
D2: ÎNTREBĂRI - SEPTEMBRIE 2024 | F2: legea lui Ohm, legile lui Kirchhoff, circuit RLC, conexiuni stea, triunghi transformator, motor, masina sincrona asincrona
C4: ELECTROTEHNICĂ, MAŞINI ŞI REŢELE ELECTRICE | N4: Total | O4: Parcurs | P4: Ramas
N5: 861 | O5: =COUNTA(I7:I31) -> 25 | P5: =N5-O5 -> 836
A6: Nr. | B6: Nr. | C6: SEPTEMBRIE 2024 Enunt | D6: Varianta a | E6: Varianta b | F6: Varianta c | I6: Raspuns | J6: verif | K6: var a | L6: var b | M6: var c | O6: =O5/N5 -> 0.029036005
A7: 1 | B7: {=_xlfn._xlws.FILTER(Sheet1!A6:K866,Sheet1!A6:A866=RANDBETWEEN(1,861),"Fatal ERROR, this PC will explode in about 1 minute")} -> 558 | C7: Legarea conductoarelor din cupru la aparate, maşini, elemente metalice fixe, se face (de regulă) prin strângere mecanică cu şuruburi în cazul conductoarelor cu secţiuni mai mici sau egale cu: | D7: 16 mmp | E7: 10 mmp | F7: 6 mmp | G7: 0 | H7: 0 | I7: NECOMPLETAT | J7: …...... | K7: b | L7: …......
A8: 2 | B8: {=_xlfn._xlws.FILTER(Sheet1!A7:K867,Sheet1!A7:A867=RANDBETWEEN(1,861),"Fatal ERROR, this PC will explode in about 1 minute")} -> 738 | C8: Calitatea de autoritate contractantă pentru concesionarea bunurilor proprietate publică sau privată a statului din domeniul energetic, precum şi pentru activităţile sau serviciile publice de interes naţional și general din domeniul energiei electrice o are | D8: Ministerul de resort | E8: ANRE - Autoritatea Naţională de Reglementare în domeniul Energiei | F8: ANRSC - Autoritatea Naţională de Reglementare in domeniul Serviciilor Comunale | G8: 0 | H8: 0 | I8: NECOMPLETAT | J8: a | K8: …...... | L8: …......
A9: 3 | B9: {=_xlfn._xlws.FILTER(Sheet1!A8:K868,Sheet1!A8:A868=RANDBETWEEN(1,861),"Fatal ERROR, this PC will explode in about 1 minute")} -> 309 | C9: La instalaţiile electrice de putere de joasă tensiune, densitatea maximă de curent admisă în regim de scurtă durată la pornire este de: | D9: 35 A/mm2 pentru conductoare de aluminiu | E9: 20 A/mm2 pentru conductoare de cupru | F9: 20 A/mm2 pentru conductoare de aluminiu | G9: 0 | H9: 0 | I9: NECOMPLETAT | J9: …...... | K9: …...... | L9: c
A10: 4 | B10: {=_xlfn._xlws.FILTER(Sheet1!A9:K869,Sheet1!A9:A869=RANDBETWEEN(1,861),"Fatal ERROR, this PC will explode in about 1 minute")} -> 457 | C10: În cazul consumatorilor racordaţi direct la reţeaua de joasă tensiune a distribuitorului, pornirea directă a motoarelor trifazate se admite pentru o putere de până la: | D10: 4 kW | E10: 5,5 kW | F10: 7,5 kW | G10: 0 | H10: 0 | I10: NECOMPLETAT | J10: …...... | K10: b | L10: …......
A11: 5 | B11: {=_xlfn._xlws.FILTER(Sheet1!A10:K870,Sheet1!A10:A870=RANDBETWEEN(1,861),"Fatal ERROR, this PC will explode in about 1 minute")} -> 801 | C11: Prevederile standardului de performanţă pentru serviciul de distribuţie nu se aplică în situaţii de: | D11: Forţă majoră | E11: Evenimente accidentale determinate de angajaţii operatorului de distribuţie | F11: condiţii meteorologice deosebite | G11: 0 | H11: 0 | I11: NECOMPLETAT | J11: a | K11: …...... | L11: …......
A12: 6 | B12: {=_xlfn._xlws.FILTER(Sheet1!A11:K871,Sheet1!A11:A871=RANDBETWEEN(1,861),"Fatal ERROR, this PC will explode in about 1 minute")} -> 311 | C12: La pozarea cablurilor de branşament pe stâlpii reţelelor electrice aeriene: | D12: pentru protecţia împotriva deteriorărilor mecanice se poate prevedea introducerea cablurilor în tub metalic pe o porţiune de 2m deasupra solului | E12: pentru protecţia împotriva deteriorărilor mecanice se poate prevedea introducerea cablurilor în tub din PVC pe o porţiune de 1 m deasupra solului | F12: reglementările nu prevăd în această situaţie măsuri de protecţie împotriva deteriorărilor mecanice | G12: 0 | H12: 0 | I12: NECOMPLETAT | J12: a | K12: …...... | L12: …......
A13: 7 | B13: {=_xlfn._xlws.FILTER(Sheet1!A12:K872,Sheet1!A12:A872=RANDBETWEEN(1,861),"Fatal ERROR, this PC will explode in about 1 minute")} -> 223 | C13: Transformatoarele de măsurare de curent: | D13: pot fi racordate în circuitul primar cu înfăşurarea secundara deschisa | E13: pot fi lăsate în exploatare cu înfăşurarea secundara deschisa | F13: nu pot fi racordate in circuitul primar cu înfăşurarea secundara deschisa | G13: 0 | H13: 0 | I13: NECOMPLETAT | J13: …...... | K13: …...... | L13: c
A14: 8 | B14: {=_xlfn._xlws.FILTER(Sheet1!A13:K873,Sheet1!A13:A873=RANDBETWEEN(1,861),"Fatal ERROR, this PC will explode in about 1 minute")} -> 417 | C14: Curentul de scurtcircuit reprezintă: | D14: curentul nominal admisibil | E14: supracurentul rezultat dintr-un scurtcircuit datorat unei conectări incorecte într-un circuit electric | F14: numai supracurentul rezultat în cazul dintr-un scurtcircuit datorat unui defect | G14: 0 | H14: 0 | I14: NECOMPLETAT | J14: …...... | K14: b | L14: …......
A15: 9 | B15: {=_xlfn._xlws.FILTER(Sheet1!A14:K874,Sheet1!A14:A874=RANDBETWEEN(1,861),"Fatal ERROR, this PC will explode in about 1 minute")} -> 628 | C15: Prevederile normativului I 7 – 2011 se aplică la proiectarea, execuţia şi exploatarea instalaţiilor electrice aferente: | D15: clădirilor prefabricate; | E15: minelor şi carierelor | F15: depozitelor de materiale pirotehnice şi explozive | G15: 0 | H15: 0 | I15: NECOMPLETAT | J15: a | K15: …...... | L15: …......
A16: 10 | B16: {=_xlfn._xlws.FILTER(Sheet1!A15:K875,Sheet1!A15:A875=RANDBETWEEN(1,861),"Fatal ERROR, this PC will explode in about 1 minute")} -> 178 | C16: Puterea electrică reactivă: | D16: permite definirea limitelor de utilizare ale unui aparat electric | E16: produce transformarea energiei electrice în energie mecanică | F16: este variaţia în timp a energiei magnetice şi electrice | G16: 0 | H16: 0 | I16: NECOMPLETAT | J16: …...... | K16: …...... | L16: c
A17: 11 | B17: {=_xlfn._xlws.FILTER(Sheet1!A16:K876,Sheet1!A16:A876=RANDBETWEEN(1,861),"Fatal ERROR, this PC will explode in about 1 minute")} -> 718 | C17: Punctele de măsurare din subcategoria C3 sunt puncte de măsurare dotate cu grupuri de măsurare: | D17: capabile să asigure date de măsurare la intervale de 60 de minute şi transmiterea bidirecţională a acestora la sistemul central de gestiune a datelor de măsurare la fiecare 24 de ore | E17: capabile să asigure date de măsurare la intervale de 15 minute şi transmiterea bidirecţională a acestora la sistemul central de gestiune a datelor de măsurare la fiecare 15 minute | F17: cu citire locală | G17: 0 | H17: 0 | I17: NECOMPLETAT | J17: …...... | K17: …...... | L17: c
A18: 12 | B18: {=_xlfn._xlws.FILTER(Sheet1!A17:K877,Sheet1!A17:A877=RANDBETWEEN(1,861),"Fatal ERROR, this PC will explode in about 1 minute")} -> 817 | C18: Contractul de distribuție se poate încheia între operatorul de distribuție și | D18: furnizorul clientului final, întotdeauna | E18: clientul final, în anumite situaţii | F18: furnizor şi clientul final | G18: 0 | H18: 0 | I18: NECOMPLETAT | J18: a | K18: …...... | L18: …......
... A31: 25 | B31: {=_xlfn._xlws.FILTER(Sheet1!A30:K890,Sheet1!A30:A890=RANDBETWEEN(1,861),"Fatal ERROR, this PC will explode in about 1 minute")} -> 722 | C31: O persoană care deţinea în proprietate sau în folosinţă o reţea electrică de distribuţie proprie la data intrării în vigoare Legii nr,123/2012: | D31: nu are obligaţii privind asigurarea accesului la reţea | E31: este obligată să asigure accesul la reţea numai pentru producători de energie electrică din surse regenerabile | F31: este obligată să asigure accesul la reţea, conform reglementărilor autorităţii competente | G31: 0 | H31: 0 | I31: NECOMPLETAT | J31: …...... | K31: …...... | L31: c

Sheet Sheet2
G2: RESPUNS INITIAL | H2: RASPUNS NOU
A3: 193 | B3: Carcasa unei celule electrice | C3: asigură numai protecţia persoanelor împotriva atingerii accidentale a pieselor aflate sub tensiune în funcţionare normală sau a pieselor în mişcare din interiorul învelişului; | D3: asigură protecţia echipamentului electric împotriva pătrunderii corpurilor străine şi a umezelii; | E3: asigură protecţia echipamentului electric împotriva supratensiunilor. | G3: A | H3: B
A4: 207 | B4: Comparativ cu un transformator, autotransformatorul are tensiunea de scurtcircuit: | C4: mai mare | D4: egală | E4: mai mică | G4: A | H4: C
A5: 210 | B5: Spaţiul ocupat de o instalaţie capsulată depinde în principal de: | C5: curentul nominal al legăturilor electrice; | D5: mediul de stingere a arcului electric; | E5: realizarea capsulării: capsulare tripolară sau monopolară. | G5: C | H5: B
A6: 214 | B6: Rolul conservatorului de ulei la transformatoarele de forţa este: | C6: de a asigura o suprafaţa de contact a uleiului cu aerul mai mica | D6: numai de a asigura spaţiul necesar dilatării si contractării uleiului | E6: de a face posibila umplerea cu ulei a transformatorului | G6: B | H6: C
A7: 233 | B7: Sistemul de tensiuni al unei reţele racordate la un generator electric care produce tensiuni electromotoare simetrice: | C7: este întotdeauna simetric | D7: este simetric chiar dacă fazele sunt neegal încărcate | E7: este simetric dacă fazele sunt egal încărcate | G7: A | H7: C
